bfit/__init__.py
bfit/_slater.py
bfit/density.py
bfit/fit.py
bfit/greedy.py
bfit/grid.py
bfit/measure.py
bfit/model.py
bfit/parse_ugbs.py
bfit/data/README.md
bfit/data/data.tar
bfit/data/kl_fpi_results.json
bfit/data/kl_fpi_results.npz
bfit/data/kl_slsqp_results.json
bfit/data/kl_slsqp_results.npz
bfit/data/ygbs
bfit/data/anion/c.an
bfit/data/anion/h.an
bfit/data/cation/c.cat
bfit/data/cation/cs.cat
bfit/data/cation/xe.cat
bfit/data/neutral/ag.slater
bfit/data/neutral/b.slater
bfit/data/neutral/be.slater
bfit/data/neutral/c.slater
bfit/data/neutral/ce.slater
bfit/data/neutral/cl.slater
bfit/data/neutral/cr.slater
bfit/data/neutral/cs.slater
bfit/data/neutral/dy.slater
bfit/data/neutral/h.slater
bfit/data/neutral/he.slater
bfit/data/neutral/i.slater
bfit/data/neutral/k.slater
bfit/data/neutral/li.slater
bfit/data/neutral/lr.slater
bfit/data/neutral/ne.slater
bfit/data/neutral/p.slater
bfit/data/neutral/rn.slater
bfit/data/neutral/xe.slater
bfit/test/__init__.py
bfit/test/test_density.py
bfit/test/test_fit.py
bfit/test/test_greedy.py
bfit/test/test_grid.py
bfit/test/test_measure.py
bfit/test/test_model.py
bfit/test/test_slater.py
qc_BFit-0.1.2.dist-info/LICENSE
qc_BFit-0.1.2.dist-info/METADATA
qc_BFit-0.1.2.dist-info/WHEEL
qc_BFit-0.1.2.dist-info/top_level.txt
qc_BFit-0.1.2.dist-info/zip-safe
qc_BFit-0.1.2.dist-info/RECORD
