Metadata-Version: 2.1
Name: qc-BFit
Version: 0.1.2
Summary: Fitting a convex sum of Gaussian functions to any probability distribution.
Author-email: QC-Devs Community <qcdevs@gmail.com>
License: GNU GENERAL PUBLIC LICENSE
Project-URL: homepage, https://github.com/theochem/bfit
Project-URL: documentation, https://bfit.qcdevs.org/
Project-URL: repository, https://github.com/theochem/bfit
Platform: Linux
Platform: Windows
Platform: MacOS
Classifier: Development Status :: 5 - Production/Stable
Classifier: Environment :: Console
Classifier: License :: OSI Approved :: GNU General Public License v3 (GPLv3)
Classifier: Natural Language :: English
Classifier: Operating System :: MacOS
Classifier: Operating System :: Microsoft :: Windows
Classifier: Operating System :: Unix
Classifier: Operating System :: POSIX
Classifier: Operating System :: POSIX :: Linux
Classifier: Programming Language :: Python
Classifier: Programming Language :: Python :: 3
Classifier: Programming Language :: Python :: 3.9
Classifier: Programming Language :: Python :: 3.10
Classifier: Programming Language :: Python :: 3.11
Classifier: Programming Language :: Python :: 3.12
Classifier: Topic :: Scientific/Engineering
Requires-Python: >=3.9
License-File: LICENSE
Provides-Extra: docs
Requires-Dist: sphinx >=2.3.0 ; extra == 'docs'
Requires-Dist: numpydoc ; extra == 'docs'
Requires-Dist: sphinx-copybutton ; extra == 'docs'
Requires-Dist: sphinx-autoapi ; extra == 'docs'
Requires-Dist: nbsphinx ; extra == 'docs'
Requires-Dist: sphinx-rtd-theme ; extra == 'docs'
